{"cameraMode":{"drawMode":0,"name":"Shaded","section":"Shading Mode"},"sceneLighting":true,"audioPlay":false,"sceneViewState":{"m_AlwaysRefresh":false,"showFog":true,"showSkybox":true,"showFlares":true,"showImageEffects":true,"showParticleSystems":true,"showVisualEffectGraphs":true,"m_FxEnabled":true},"in2DMode":false,"pivot":{"x":-2.7949020862579347,"y":1.2300680875778199,"z":17.386764526367189},"rotation":{"x":-0.004804129246622324,"y":0.048577044159173968,"z":-0.00023386196698993444,"w":-0.9988097548484802},"size":30.48391342163086,"orthographic":false}